turbo_lambda/__init__.py
turbo_lambda/decorators.py
turbo_lambda/errors.py
turbo_lambda/log.py
turbo_lambda/py.typed
turbo_lambda/schemas.py
turbo_lambda/scripts/__init__.py
turbo_lambda/scripts/update_turbo_lambda_layer.py
turbo_lambda/version.py
turbo_lambda-0.6.2.dist-info/WHEEL
turbo_lambda-0.6.2.dist-info/entry_points.txt
turbo_lambda-0.6.2.dist-info/METADATA
turbo_lambda-0.6.2.dist-info/RECORD
