Metadata-Version: 2.3
Name: turbo-lambda
Version: 0.6.2
Summary: Turbo Lambda Description
Author: Sam Mosleh
Author-email: Sam Mosleh <sam.mosleh.d@gmail.com>
Requires-Dist: opentelemetry-api>=1.27.0
Requires-Dist: pydantic-settings>=2.11.0
Requires-Python: >=3.12
